dify_user_client/__init__.py
dify_user_client/apps.py
dify_user_client/base.py
dify_user_client/clients.py
dify_user_client/knowledge.py
dify_user_client/llms.py
dify_user_client/main.py
dify_user_client/tools.py
dify_user_client/models/__init__.py
dify_user_client/models/app.py
dify_user_client/models/base.py
dify_user_client/models/knowledge.py
dify_user_client/models/llm.py
dify_user_client/models/logs.py
dify_user_client/models/pagination.py
dify_user_client/models/tool.py
dify_user_client/models/workflow.py
dify_user_client-0.2.1.dist-info/METADATA
dify_user_client-0.2.1.dist-info/WHEEL
dify_user_client-0.2.1.dist-info/licenses/LICENSE
dify_user_client-0.2.1.dist-info/RECORD
