Metadata-Version: 2.4
Name: dify-user-client
Version: 0.2.1
Summary: A Python utility library for interacting with Dify as if you were using the UI. Perform any action available through the user interface.
Project-URL: Homepage, https://github.com/ivan-pikulin/dify_user_client
Project-URL: Documentation, https://ivan-pikulin.github.io/dify_user_client/
License-File: LICENSE
Requires-Python: >=3.11
Requires-Dist: pydantic>=2.11.3
Requires-Dist: pyyaml>=6.0.2
Requires-Dist: requests>=2.32.3
Requires-Dist: sphinx-rtd-theme>=3.0.2
Provides-Extra: dev
Requires-Dist: ipykernel>=6.29.0; extra == 'dev'
Requires-Dist: pytest>=8.3.5; extra == 'dev'
Requires-Dist: python-dotenv>=1.1.0; extra == 'dev'
